redgram/RedGram.py
redgram/__init__.py
RedGram-0.9.0.dist-info/LICENSE
RedGram-0.9.0.dist-info/METADATA
RedGram-0.9.0.dist-info/WHEEL
RedGram-0.9.0.dist-info/top_level.txt
RedGram-0.9.0.dist-info/RECORD
